arp_jarvis_run_coordinator-0.3.8.dist-info/licenses/LICENSE
jarvis_run_coordinator/__init__.py
jarvis_run_coordinator/__main__.py
jarvis_run_coordinator/app.py
jarvis_run_coordinator/auth.py
jarvis_run_coordinator/coordinator.py
jarvis_run_coordinator/utils.py
jarvis_run_coordinator/clients/__init__.py
jarvis_run_coordinator/clients/artifact_store.py
jarvis_run_coordinator/clients/atomic_executor_client.py
jarvis_run_coordinator/clients/composite_executor_client.py
jarvis_run_coordinator/clients/event_stream.py
jarvis_run_coordinator/clients/interfaces.py
jarvis_run_coordinator/clients/node_registry_client.py
jarvis_run_coordinator/clients/pdp_client.py
jarvis_run_coordinator/clients/run_store.py
jarvis_run_coordinator/clients/selection_client.py
scripts/send_request.py
arp_jarvis_run_coordinator-0.3.8.dist-info/METADATA
arp_jarvis_run_coordinator-0.3.8.dist-info/WHEEL
arp_jarvis_run_coordinator-0.3.8.dist-info/entry_points.txt
arp_jarvis_run_coordinator-0.3.8.dist-info/top_level.txt
arp_jarvis_run_coordinator-0.3.8.dist-info/RECORD
